{
    "alvaro": {
        "name": "alvaro",
        "password": "JDJhJDEwJElSNVlmVnlXT1hiWmc0Qnlva0JkRU8ub3dNdXZDZHBhVEJ1OHJwNkxwdkF0cHVOWi4uRzlP",
        "key": "ibLpzD4nQHN1M9LjwC57uJIGbL9ZPPFNIj1T74aQ+4s=",
        "files": {
            "files": [
                {
                    "id": 1,
                    "file": "ejemplo.txt",
                    "size": 8,
                    "time": "2018-05-28T17:48:59.679342811+02:00"
                },
                {
                    "id": 2,
                    "file": "ejemplo2.txt",
                    "size": 21,
                    "time": "2018-05-29T18:27:03.856152+02:00"
                }
            ]
        }
    }
}